rclone_api/__init__.py
rclone_api/cli.py
rclone_api/completed_process.py
rclone_api/config.py
rclone_api/convert.py
rclone_api/deprecated.py
rclone_api/diff.py
rclone_api/dir.py
rclone_api/dir_listing.py
rclone_api/exec.py
rclone_api/file.py
rclone_api/file_item.py
rclone_api/file_part.py
rclone_api/file_stream.py
rclone_api/filelist.py
rclone_api/group_files.py
rclone_api/http_server.py
rclone_api/install.py
rclone_api/log.py
rclone_api/mount.py
rclone_api/mount_util.py
rclone_api/process.py
rclone_api/rclone_impl.py
rclone_api/remote.py
rclone_api/rpath.py
rclone_api/scan_missing_folders.py
rclone_api/types.py
rclone_api/util.py
rclone_api/assets/example.txt
rclone_api/cmd/analyze.py
rclone_api/cmd/copy_large_s3.py
rclone_api/cmd/copy_large_s3_finish.py
rclone_api/cmd/install_rclone.py
rclone_api/cmd/list_files.py
rclone_api/cmd/save_to_db.py
rclone_api/db/__init__.py
rclone_api/db/db.py
rclone_api/db/models.py
rclone_api/detail/copy_file_parts_resumable.py
rclone_api/detail/walk.py
rclone_api/experimental/flags.py
rclone_api/experimental/flags_base.py
rclone_api/fs/filesystem.py
rclone_api/fs/walk.py
rclone_api/fs/walk_threaded.py
rclone_api/fs/walk_threaded_walker.py
rclone_api/s3/api.py
rclone_api/s3/basic_ops.py
rclone_api/s3/chunk_task.py
rclone_api/s3/create.py
rclone_api/s3/types.py
rclone_api/s3/multipart/file_info.py
rclone_api/s3/multipart/finished_piece.py
rclone_api/s3/multipart/info_json.py
rclone_api/s3/multipart/merge_state.py
rclone_api/s3/multipart/upload_info.py
rclone_api/s3/multipart/upload_parts_inline.py
rclone_api/s3/multipart/upload_parts_resumable.py
rclone_api/s3/multipart/upload_parts_server_side_merge.py
rclone_api/s3/multipart/upload_state.py
rclone_api-1.5.73.dist-info/licenses/LICENSE
rclone_api-1.5.73.dist-info/METADATA
rclone_api-1.5.73.dist-info/WHEEL
rclone_api-1.5.73.dist-info/entry_points.txt
rclone_api-1.5.73.dist-info/top_level.txt
rclone_api-1.5.73.dist-info/RECORD
