Metadata-Version: 2.4
Name: rclone_api
Version: 1.5.73
Summary: rclone api in python
Home-page: https://github.com/zackees/rclone-api
License: BSD 3-Clause License
Keywords: rclone,api,python,fast,sftp,s3,backblaze
Classifier: Programming Language :: Python :: 3
Requires-Python: >=3.10
License-File: LICENSE
Requires-Dist: pyright>=1.1.393
Requires-Dist: python-dotenv>=1.0.0
Requires-Dist: certifi>=2025.1.31
Requires-Dist: psutil
Requires-Dist: sqlmodel>=0.0.23
Requires-Dist: psycopg2-binary>=2.9.10
Requires-Dist: httpx>=0.28.1
Requires-Dist: download>=0.3.5
Requires-Dist: appdirs>=1.4.4
Requires-Dist: beautifulsoup4>=4.13.3
Requires-Dist: boto3>=1.28.23
Dynamic: home-page
Dynamic: license-file
